MANIFEST.in
README.rst
setup.cfg
setup.py
docs/.DS_Store
docs/.gitignore
docs/Makefile
docs/api.rst
docs/conf.py
docs/index.rst
docs/releases.rst
docs/shell.rst
docs/_build/.DS_Store
docs/_build/doctrees/.DS_Store
docs/_build/doctrees/api.doctree
docs/_build/doctrees/environment.pickle
docs/_build/doctrees/index.doctree
docs/_build/doctrees/releases.doctree
docs/_build/doctrees/shell.doctree
docs/_build/doctrees/api/backup_schedules.doctree
docs/_build/doctrees/api/exceptions.doctree
docs/_build/doctrees/api/flavors.doctree
docs/_build/doctrees/api/images.doctree
docs/_build/doctrees/api/index.doctree
docs/_build/doctrees/api/ipgroups.doctree
docs/_build/doctrees/api/servers.doctree
docs/_build/doctrees/ref/backup_schedules.doctree
docs/_build/doctrees/ref/exceptions.doctree
docs/_build/doctrees/ref/flavors.doctree
docs/_build/doctrees/ref/images.doctree
docs/_build/doctrees/ref/index.doctree
docs/_build/doctrees/ref/ipgroups.doctree
docs/_build/doctrees/ref/servers.doctree
docs/_build/html/.buildinfo
docs/_build/html/api.html
docs/_build/html/genindex.html
docs/_build/html/index.html
docs/_build/html/modindex.html
docs/_build/html/objects.inv
docs/_build/html/py-modindex.html
docs/_build/html/releases.html
docs/_build/html/search.html
docs/_build/html/searchindex.js
docs/_build/html/shell.html
docs/_build/html/_sources/api.txt
docs/_build/html/_sources/index.txt
docs/_build/html/_sources/releases.txt
docs/_build/html/_sources/shell.txt
docs/_build/html/_sources/api/backup_schedules.txt
docs/_build/html/_sources/api/exceptions.txt
docs/_build/html/_sources/api/flavors.txt
docs/_build/html/_sources/api/images.txt
docs/_build/html/_sources/api/index.txt
docs/_build/html/_sources/api/ipgroups.txt
docs/_build/html/_sources/api/servers.txt
docs/_build/html/_sources/ref/backup_schedules.txt
docs/_build/html/_sources/ref/exceptions.txt
docs/_build/html/_sources/ref/flavors.txt
docs/_build/html/_sources/ref/images.txt
docs/_build/html/_sources/ref/index.txt
python_ukcloudservers.egg-info/PKG-INFO
python_ukcloudservers.egg-info/SOURCES.txt
python_ukcloudservers.egg-info/dependency_links.txt
python_ukcloudservers.egg-info/entry_points.txt
python_ukcloudservers.egg-info/requires.txt
python_ukcloudservers.egg-info/top_level.txt
