Metadata-Version: 1.0
Name: python-ukcloudservers
Version: 1.2
Summary: Client library for Rackspace's Cloud Servers API
Home-page: http://packages.python.org/python-ukcloudservers
Author: Jacob Kaplan-Moss
Author-email: jacob@jacobian.org
License: BSD
Platform: UNKNOWN
Classifier: Development Status :: 5 - Production/Stable
Classifier: Environment :: Console
Classifier: Intended Audience :: Developers
Classifier: Intended Audience :: Information Technology
Classifier: License :: OSI Approved :: BSD License
Classifier: Operating System :: OS Independent
Classifier: Programming Language :: Python
